brainbox/__init__.py
brainbox/core.py
brainbox/ephys_plots.py
brainbox/plot.py
brainbox/plot_base.py
brainbox/processing.py
brainbox/singlecell.py
brainbox/video.py
brainbox/behavior/__init__.py
brainbox/behavior/dlc.py
brainbox/behavior/training.py
brainbox/behavior/wheel.py
brainbox/io/__init__.py
brainbox/io/one.py
brainbox/io/spikeglx.py
brainbox/metrics/__init__.py
brainbox/metrics/electrode_drift.py
brainbox/metrics/single_units.py
brainbox/population/__init__.py
brainbox/population/cca.py
brainbox/population/decode.py
brainbox/task/__init__.py
brainbox/task/_knockoff.py
brainbox/task/_statsmodels.py
brainbox/task/closed_loop.py
brainbox/task/passive.py
brainbox/task/trials.py
brainbox/tests/__init__.py
brainbox/tests/test_behavior.py
brainbox/tests/test_cca.py
brainbox/tests/test_io.py
brainbox/tests/test_metrics.py
brainbox/tests/test_passive.py
brainbox/tests/test_plot_base.py
brainbox/tests/test_population.py
brainbox/tests/test_processing.py
brainbox/tests/test_singlecell.py
brainbox/tests/test_task.py
brainbox/tests/test_trials.py
brainbox/tests/test_video.py
brainbox/tests/fixtures/ephys_test.p
brainbox/tests/fixtures/parquet_records.json
brainbox/tests/fixtures/trials_df_test.csv
brainbox/tests/fixtures/trials_test.pickle
brainbox/tests/fixtures/wheel_test.p
examples/__init__.py
examples/one/__init__.py
examples/one/docs_one_queries.py
examples/one/one_queries.py
ibllib/__init__.py
ibllib/exceptions.py
ibllib/time.py
ibllib/ephys/__init__.py
ibllib/ephys/ephysqc.py
ibllib/ephys/spikes.py
ibllib/ephys/sync_probes.py
ibllib/io/__init__.py
ibllib/io/ffmpeg.py
ibllib/io/flags.py
ibllib/io/misc.py
ibllib/io/raw_daq_loaders.py
ibllib/io/raw_data_loaders.py
ibllib/io/session_params.py
ibllib/io/video.py
ibllib/io/extractors/__init__.py
ibllib/io/extractors/base.py
ibllib/io/extractors/biased_trials.py
ibllib/io/extractors/bpod_trials.py
ibllib/io/extractors/camera.py
ibllib/io/extractors/default_channel_maps.py
ibllib/io/extractors/ephys_fpga.py
ibllib-3.4.1.dist-info/LICENSE
ibllib-3.4.1.dist-info/METADATA
ibllib-3.4.1.dist-info/WHEEL
ibllib-3.4.1.dist-info/entry_points.txt
ibllib-3.4.1.dist-info/top_level.txt
ibllib-3.4.1.dist-info/RECORD
