Metadata-Version: 2.1
Name: ibllib
Version: 3.4.1
Summary: IBL libraries
Home-page: https://www.internationalbrainlab.com/
Author: IBL Staff
License: MIT
Requires-Python: >=3.10
Provides-Extra: wfield
License-File: LICENSE
